minesweeper_vim/game.py
minesweeper_vim/ui.py
minesweeper_vim-0.1.1.dist-info/entry_points.txt
minesweeper_vim-0.1.1.dist-info/LICENSE
minesweeper_vim-0.1.1.dist-info/WHEEL
minesweeper_vim-0.1.1.dist-info/METADATA
minesweeper_vim-0.1.1.dist-info/RECORD
