Metadata-Version: 2.1
Name: minesweeper-vim
Version: 0.1.1
Summary: Curses minesweeper with vim bindings
License: MIT
Author: Brian Cho
Author-email: briandcho@yahoo.com
Requires-Python: >=3.8,<4.0
Classifier: License :: OSI Approved :: MIT License
Classifier: Programming Language :: Python :: 3
Classifier: Programming Language :: Python :: 3.8
Classifier: Programming Language :: Python :: 3.9
Requires-Dist: typer (>=0.3.2,<0.4.0)
